mysql_rds/__init__.py
mysql_rds/backend/__init__.py
mysql_rds/backend/base.py
mysql_rds/backend/client.py
mysql_rds/backend/creation.py
django_mysql_rds-1.0.0.dist-info/LICENSE
django_mysql_rds-1.0.0.dist-info/METADATA
django_mysql_rds-1.0.0.dist-info/WHEEL
django_mysql_rds-1.0.0.dist-info/top_level.txt
django_mysql_rds-1.0.0.dist-info/RECORD
