Metadata-Version: 2.1
Name: django-mysql-rds
Version: 1.0.0
Summary: UNKNOWN
Home-page: https://github.com/cramshaw/django-mysql-rds
Author: Chris Ramshaw
Author-email: chris.ramshaw@nanoporetech.com
License: Mozilla Public License 2.0 (MPL 2.0)
Platform: UNKNOWN
Classifier: Environment :: Web Environment
Classifier: Framework :: Django
Classifier: Framework :: Django :: 3.2
Classifier: Intended Audience :: Developers
Classifier: License :: OSI Approved :: Mozilla Public License 2.0 (MPL 2.0)
Classifier: Operating System :: OS Independent
Classifier: Programming Language :: Python
Classifier: Programming Language :: Python :: 3.7
License-File: LICENSE
